rq_mr.py
rq_mr-0.2.0.dist-info/METADATA
rq_mr-0.2.0.dist-info/WHEEL
rq_mr-0.2.0.dist-info/RECORD
