Metadata-Version: 2.1
Name: rq-mr
Version: 0.2.0
Summary: MapReduce technique over RQ
Author: Biel Cardona
Author-email: bielcardona@gmail.com
Requires-Python: >=3.11
Classifier: Programming Language :: Python :: 3
Classifier: Programming Language :: Python :: 3.11
Classifier: Programming Language :: Python :: 3.12
Classifier: Programming Language :: Python :: 3.13
Requires-Dist: redis (>=5.2.1,<6.0.0)
Requires-Dist: rq (>=2.1.0,<3.0.0)
